Metadata-Version: 2.1
Name: fdups
Version: 0.0.1
Summary: Finds all duplicate files in a list of files and folders
Home-page: https://github.com/xloop10/fdups
Author: Ivaylo Ivanov
Author-email: i.ivanov.2250@gmail.com
License: MIT
Platform: UNKNOWN
Classifier: Programming Language :: Python :: 2.7
Classifier: License :: OSI Approved :: MIT License
Classifier: Operating System :: Microsoft :: Windows
Classifier: Topic :: Utilities
